pedagio.v
module pedagio (
// Entradas de Controle e Dados
input wire ready,                      // Sinal de confirmação de cobrança
input wire reset,                      // Sinal de reset assíncrono
input wire clk,                        // Clock para a lógica sequencial
input wire [1:0] Eixos,                // Número de eixos (2 a 5+)
input wire [3:0] Peso,                 // Peso total em toneladas (0 a 15t)

// Saídas de Display (7 segmentos)
output reg [6:0] S,                    // Saída do display da categoria
output reg [6:0] S0,                   // Display das unidades do valor total
output reg [6:0] S1,                   // Display das dezenas do valor total
output reg [6:0] S2,                   // Display das centenas do valor total
output reg [6:0] S3                    // Display dos milhares do valor total
);

// Sinais de classificação combinacional
wire Categoria1, Categoria2, Categoria3, peso_maior_12t, peso_menor_igual_12t;

// Determina limites de peso
assign peso_maior_12t = (Peso > 4'd12);
assign peso_menor_igual_12t = (Peso <= 4'd12);

// Lógica para determinar a Categoria 1 (peso <= 7t e eixos = 2)
assign Categoria1 = (Peso <= 4'd7) & (Eixos == 2'b00);

// Lógica para determinar a Categoria 2 (peso <= 12t e eixos = 3)
assign Categoria2 = peso_menor_igual_12t & (Eixos == 2'b01);

// Lógica para determinar a Categoria 3 (peso > 12t e eixos >= 4)
assign Categoria3 = peso_maior_12t & (Eixos >= 2'b10);

// Decodificador de Categoria
always @(*) begin
    S = 7'b0110000;                    // Padrão 'E' (Erro)

    if (Categoria1)
        S = 7'b1001111;                // Exibe '1'
    else if (Categoria2)
        S = 7'b0010010;                // Exibe '2'
    else if (Categoria3)
        S = 7'b0000110;                // Exibe '3'
end

// Valor da categoria (lógica combinacional)
reg [7:0] valor;

always @(*) begin
    valor = 8'd0;                      // Padrão para Erro
    if (Categoria1)
        valor = 8'd10;                 // Categoria 1: 10 unidades
    else if (Categoria2)
        valor = 8'd25;                 // Categoria 2: 25 unidades
    else if (Categoria3)
        valor = 8'd50;                 // Categoria 3: 50 unidades
end

// Registradores BCD para o valor total faturado
reg antigoReady;                       // Armazena estado anterior do READY
reg [3:0] d0;                          // Dígito das unidades
reg [3:0] d1;                          // Dígito das dezenas
reg [3:0] d2;                          // Dígito das centenas
reg [3:0] d3;                          // Dígito dos milhares

// Lógica sequencial (Acumulação do total)
always @(posedge clk) begin

    if (reset) begin                   // Reset assíncrono
        d0 <= 0;
        d1 <= 0;
        d2 <= 0;
        d3 <= 0;
        antigoReady <= 0;
    end
    else begin

        // Variáveis internas para cálculos BCD usando atribuições bloqueantes
        reg [3:0] temp_d0, temp_d1, temp_d2;
        reg carry_d0_to_d1, carry_d1_to_d2, carry_d2_to_d3;
        
        // Inicializa as variáveis temporárias
        temp_d0 = d0;
        temp_d1 = d1;
        temp_d2 = d2;
        carry_d0_to_d1 = 1'b0;
        carry_d1_to_d2 = 1'b0;
        carry_d2_to_d3 = 1'b0;

        // Detecta a borda de subida do READY para realizar a cobrança
        if (antigoReady == 0 && ready == 1) begin 

            case (valor)

                // Soma 10 unidades
                8'd10: begin
                    temp_d1 = d1 + 1;                           // Adiciona 1 à dezena
                    carry_d1_to_d2 = (temp_d1 > 9);             // Verifica carry para d2
                    if (carry_d1_to_d2) temp_d1 = temp_d1 - 10;
                end

                // Soma 25 unidades
                8'd25: begin
                    // 1. Soma 5 às unidades (d0)
                    temp_d0 = d0 + 5;
                    carry_d0_to_d1 = (temp_d0 > 9);             // Verifica carry para d1
                    if (carry_d0_to_d1) temp_d0 = temp_d0 - 10;

                    // 2. Soma 2 às dezenas (d1) + o carry gerado por d0
                    temp_d1 = d1 + 2 + carry_d0_to_d1;
                    carry_d1_to_d2 = (temp_d1 > 9);             // Verifica carry para d2
                    if (carry_d1_to_d2) temp_d1 = temp_d1 - 10;
                end

                // Soma 50 unidades
                8'd50: begin
                    temp_d1 = d1 + 5;                           // Adiciona 5 à dezena
                    carry_d1_to_d2 = (temp_d1 > 9);             // Verifica carry para d2
                    if (carry_d1_to_d2) temp_d1 = temp_d1 - 10;
                end
                
            endcase
            
            // Propagação de Carries D2 e D3
            
            // Adiciona carry c1 (se houver) ao d2
            temp_d2 = d2 + carry_d1_to_d2;
            carry_d2_to_d3 = (temp_d2 > 9);                     // Verifica carry para d3
            if (carry_d2_to_d3) temp_d2 = temp_d2 - 10;

            // Aplica as atualizações de estado (Não Bloqueantes)
            
            d0 <= temp_d0;
            d1 <= temp_d1;
            d2 <= temp_d2;
            
            // Atualiza d3 (milhares) apenas se houver carry de d2
            if (carry_d2_to_d3)
                d3 <= d3 + 1;
            
        end 

        // Atualiza o valor anterior do READY para detecção de borda no próximo ciclo
        antigoReady <= ready;

    end

end

// Decodificadores BCD para 7 segmentos (d0: Unidades)
always @(*) begin
    case(d0)
    4'd0: S0 = 7'b1000000;
    4'd1: S0 = 7'b1111001;
    4'd2: S0 = 7'b0100100;
    4'd3: S0 = 7'b0110000;
    4'd4: S0 = 7'b0011001;
    4'd5: S0 = 7'b0010010;
    4'd6: S0 = 7'b0000010;
    4'd7: S0 = 7'b1111000;
    4'd8: S0 = 7'b0000000;
    4'd9: S0 = 7'b0010000;
    default: S0 = 7'b0110000; // Caso indefinido
    endcase

// Decodificadores BCD para 7 segmentos (d1: Dezenas)
    case(d1)
    4'd0: S1 = 7'b1000000;
    4'd1: S1 = 7'b1111001;
    4'd2: S1 = 7'b0100100;
    4'd3: S1 = 7'b0110000;
    4'd4: S1 = 7'b0011001;
    4'd5: S1 = 7'b0010010;
    4'd6: S1 = 7'b0000010;
    4'd7: S1 = 7'b1111000;
    4'd8: S1 = 7'b0000000;
    4'd9: S1 = 7'b0010000;
    default: S1 = 7'b0110000;
    endcase

// Decodificadores BCD para 7 segmentos (d2: Centenas)
    case(d2)
    4'd0: S2 = 7'b1000000;
    4'd1: S2 = 7'b1111001;
    4'd2: S2 = 7'b0100100;
    4'd3: S2 = 7'b0110000;
    4'd4: S2 = 7'b0011001;
    4'd5: S2 = 7'b0010010;
    4'd6: S2 = 7'b0000010;
    4'd7: S2 = 7'b1111000;
    4'd8: S2 = 7'b0000000;
    4'd9: S2 = 7'b0010000;
    default: S2 = 7'b0110000;
    endcase

// Decodificadores BCD para 7 segmentos (d3: Milhares)
    case(d3)
    4'd0: S3 = 7'b1000000;
    4'd1: S3 = 7'b1111001;
    4'd2: S3 = 7'b0100100;
    4'd3: S3 = 7'b0110000;
    4'd4: S3 = 7'b0011001;
    4'd5: S3 = 7'b0010010;
    4'd6: S3 = 7'b0000010;
    4'd7: S3 = 7'b1111000;
    4'd8: S3 = 7'b0000000;
    4'd9: S3 = 7'b0010000;
    default: S3 = 7'b0110000;
    endcase

end

endmodule

tb_pedagio.v
`timescale 1ns/1ns

module tb_pedagio;

// Declaração de sinais
reg ready;
reg reset;
reg clk;
reg [1:0] Eixos;                       // 2 bits (00 a 11) [4]
reg [3:0] Peso;                        // 4 bits (0 a 15t) [4]

// Saídas (Displays)
wire [6:0] S;                          // Display da categoria [1]
wire [6:0] S0;                         // Unidades [1]
wire [6:0] S1;                         // Dezenas [1]
wire [6:0] S2;                         // Centenas [1]
wire [6:0] S3;                         // Milhares [1]


// NSTANCIAÇÃO DO MÓDULO (DUT)

pedagio DUT (
    .ready(ready),
    .reset(reset),
    .clk(clk),
    .Eixos(Eixos),
    .Peso(Peso),
    .S(S),
    .S0(S0),
    .S1(S1),
    .S2(S2),
    .S3(S3)
);

// GERAÇÃO DO CLOCK (período de 10ns)

initial begin
    clk = 0;
    forever #5 clk = ~clk;             // Gera um clock com período de 10ns
end

// INICIALIZAÇÃO E MONITORAMENTO

initial begin
    $dumpfile("pedagio_sim.vcd");      // Arquivo de simulação de ondas
    $dumpvars(0, tb_pedagio);          // Salva todas as variáveis
    
    // Monitora o estado atual do sistema (útil para debug via console)
    $monitor("T=%0t | Rst=%b | Rdy=%b | Eixos=%b | Peso=%d | Categoria(S)=%b | Valor=%d | Total=d3:%d d2:%d d1:%d d0:%d",
             $time, reset, ready, Eixos, Peso, S, DUT.valor, DUT.d3, DUT.d2, DUT.d1, DUT.d0);
end

// BLOCO DE ESTÍMULO

initial begin
    // ESTADO INICIAL
    reset = 1;                         // Reseta o sistema
    ready = 0;
    Eixos = 2'b00;
    Peso = 4'd0;
    #10;
    
    // LIBERAÇÃO DO RESET
    reset = 0;
    #5;

    // TESTE 1: CATEGORIA 1 (Valor: 10)
    // Condição: Peso <= 7t (5t) e Eixos = 2 (00)
    // Total Esperado: 10

    $display("\n--- [T1] C1 (10) ---");
    Eixos = 2'b00;
    Peso = 4'd5;
    #5; 

    // Confirma Cobrança (Aciona Ready)
    ready = 1;
    #10;                               // Aguarda 1 ciclo de clock para a transição sequencial
    ready = 0;
    #5;

    // TESTE 2: CATEGORIA 3 (Valor: 50)
    // Condição: Peso > 12t (13t) e Eixos >= 4 (10)
    // Total Esperado: 10 + 50 = 60

    $display("\n--- [T2] C3 (50) ---");
    Eixos = 2'b10;
    Peso = 4'd13;
    #5;
    
    // Confirma Cobrança
    ready = 1;
    #10; 
    ready = 0;
    #5;
    
    // TESTE 3: CATEGORIA 2 (Valor: 25) - Teste de Carry BCD
    // Condição: Peso <= 12t (10t) e Eixos = 3 (01)
    // Total Esperado: 60 + 25 = 85

    $display("\n--- [T3] C2 (25) ---");
    Eixos = 2'b01;
    Peso = 4'd10;
    #5;

    // Confirma Cobrança
    ready = 1;
    #10; 
    ready = 0;
    #5;
    
    // TESTE 4: ERRO (Valor: 0)
    // Condição: Combinação não prevista (ex: Peso > 7t e Eixos = 2)
    // Total Esperado: 85 + 0 = 85

    $display("\n--- [T4] ERRO (0) ---");
    Eixos = 2'b00;
    Peso = 4'd8;                       // Peso 8t, 2 eixos (não é C1 nem C2/C3)
    #5;

    // Confirma Cobrança (Valor deve ser 0, Total permanece 85)
    ready = 1;
    #10; 
    ready = 0;
    #5;


    // TESTE 5: Forçando Carry de D1 para D2 (Soma 50)
    // Estado Atual: 85. Queremos: 85 + 50 = 135

    $display("\n--- [T5] C3 (50) - Forçando Carry de 8 para 13 ---");
    Eixos = 2'b11;                     // 5 ou mais eixos
    Peso = 4'd15;                      // 15t (C3)
    #5;
    
    ready = 1;
    #10; 
    ready = 0;
    #5;                                // Total deve ser 135 (d2=1, d1=3, d0=5)


    // TESTE 6: Forçando Carry de D0 e D1 na mesma operação (+25)
    // Estado Atual: 135. Queremos: 135 + 25 = 160
    // Teste CRÍTICO da lógica BCD complexa do 'case 8'd25'

    $display("\n--- [T6] C2 (25) - Forçando Carry em D0 e D1 ---");
    Eixos = 2'b01; 
    Peso = 4'd12;                      // C2 (25)
    #5;
    
    ready = 1;
    #10; 
    ready = 0;
    #5;                                // Total deve ser 160 (d2=1, d1=6, d0=0)
    

    // FIM DA SIMULAÇÃO

    #50;
    $finish; // Encerra a simulação

end

endmodule

pedagio_sim.vcd
$date
	Thu Nov 20 14:10:33 2025
$end
$version
	Icarus Verilog
$end
$timescale
	1ns
$end
$scope module tb_pedagio $end
$var wire 7 ! S3 [6:0] $end
$var wire 7 " S2 [6:0] $end
$var wire 7 # S1 [6:0] $end
$var wire 7 $ S0 [6:0] $end
$var wire 7 % S [6:0] $end
$var reg 2 & Eixos [1:0] $end
$var reg 4 ' Peso [3:0] $end
$var reg 1 ( clk $end
$var reg 1 ) ready $end
$var reg 1 * reset $end
$scope module DUT $end
$var wire 1 + Categoria1 $end
$var wire 1 , Categoria2 $end
$var wire 1 - Categoria3 $end
$var wire 2 . Eixos [1:0] $end
$var wire 4 / Peso [3:0] $end
$var wire 1 ( clk $end
$var wire 1 ) ready $end
$var wire 1 * reset $end
$var wire 1 0 peso_menor_igual_12t $end
$var wire 1 1 peso_maior_12t $end
$var reg 7 2 S [6:0] $end
$var reg 7 3 S0 [6:0] $end
$var reg 7 4 S1 [6:0] $end
$var reg 7 5 S2 [6:0] $end
$var reg 7 6 S3 [6:0] $end
$var reg 1 7 antigoReady $end
$var reg 1 8 carry_d0_to_d1 $end
$var reg 1 9 carry_d1_to_d2 $end
$var reg 1 : carry_d2_to_d3 $end
$var reg 4 ; d0 [3:0] $end
$var reg 4 < d1 [3:0] $end
$var reg 4 = d2 [3:0] $end
$var reg 4 > d3 [3:0] $end
$var reg 4 ? temp_d0 [3:0] $end
$var reg 4 @ temp_d1 [3:0] $end
$var reg 4 A temp_d2 [3:0] $end
$var reg 8 B valor [7:0] $end
$upscope $end
$upscope $end
$enddefinitions $end
$comment Show the parameter values. $end
$dumpall
$end
#0
$dumpvars
b1010 B
bx A
bx @
bx ?
bx >
bx =
bx <
bx ;
x:
x9
x8
x7
bx 6
bx 5
bx 4
bx 3
b1001111 2
01
10
b0 /
b0 .
0-
0,
1+
1*
0)
0(
b0 '
b0 &
b1001111 %
bx $
bx #
bx "
bx !
$end
#5
b1000000 !
b1000000 6
b1000000 "
b1000000 5
b1000000 #
b1000000 4
b1000000 $
b1000000 3
07
b0 >
b0 =
b0 <
b0 ;
1(
#10
0(
0*
#15
0:
09
08
b0 A
b0 @
b0 ?
1(
b101 '
b101 /
#20
0(
1)
#25
b1111001 #
b1111001 4
17
b1 <
b1 @
1(
#30
0(
0)
#35
07
b110 %
b110 2
b110010 B
0+
1-
1(
11
00
b1101 '
b1101 /
b10 &
b10 .
#40
0(
1)
#45
b10 #
b10 4
17
b110 <
b110 @
1(
#50
0(
0)
#55
07
b11001 B
b10010 %
b10010 2
1,
0-
1(
01
10
b1010 '
b1010 /
b1 &
b1 .
#60
0(
1)
#65
b0 #
b0 4
b10010 $
b10010 3
17
b1000 <
b101 ;
b1000 @
b101 ?
1(
#70
0(
0)
#75
07
b110000 %
b110000 2
b0 B
0,
1(
b1000 '
b1000 /
b0 &
b0 .
#80
0(
1)
#85
17
1(
#90
0(
0)
#95
07
b110010 B
b110 %
b110 2
1-
1(
11
00
b1111 '
b1111 /
b11 &
b11 .
#100
0(
1)
#105
b1111001 "
b1111001 5
b110000 #
b110000 4
17
b1 =
b11 <
b1 A
19
b11 @
1(
#110
0(
0)
#115
07
b10010 %
b10010 2
b11001 B
09
1,
0-
1(
01
10
b1100 '
b1100 /
b1 &
b1 .
#120
0(
1)
#125
b10 #
b10 4
b1000000 $
b1000000 3
17
b110 <
b0 ;
b110 @
18
b0 ?
1(
#130
0(
0)
#135
07
08
1(
