DE2_115.v
module DE2_115(

    //////////// LED //////////
    output [8:0] LEDG,
    output [17:0] LEDR,

    //////////// KEY //////////
    input [3:0] KEY,

    //////////// SW //////////
    input [17:0] SW,

    //////////// SEG7 //////////
    output [6:0] HEX0,
    output [6:0] HEX1,
    output [6:0] HEX2,
    output [6:0] HEX3,
    output [6:0] HEX4,
    output [6:0] HEX5,
    output [6:0] HEX6,
    output [6:0] HEX7,

    //////////// GPIO //////////
    inout [35:0] GPIO
);
    wire [1:0] eixos = SW[1:0];
    wire [3:0] peso  = SW[5:2];

    reg [6:0] cat;
    reg [7:0] valor;

    always @(*) begin
        if (peso <= 7 && eixos == 0) begin
            cat   = 7'b1111001;  // "1"
            valor = 8'd10;
        end else if (peso <= 12 && eixos == 1) begin
            cat   = 7'b0100100;  // "2"
            valor = 8'd25;
        end else if (peso > 12 && eixos >= 2) begin
            cat   = 7'b0110000;  // "3"
            valor = 8'd50;
        end else begin
            cat   = 7'b0000110;  // "E"
            valor = 8'd0;
        end
    end

    assign HEX6 = cat;

    reg [3:0] d0=0, d1=0, d2=0, d3=0;  // Total acumulado
    reg [3:0] v0=0, v1=0;              // Valor do veículo

    // Variáveis temporárias
    reg [3:0] t0, t1, t2, t3;
    reg c1, c2, c3;
    integer x;

    always @(*) begin
        v0 = valor % 10;
        v1 = valor / 10;
    end

    always @(posedge KEY[0] or negedge KEY[2]) begin
        if (!KEY[2]) begin
            d0 <= 0; d1 <= 0; d2 <= 0; d3 <= 0;
        end else begin
            // Inicializa temporários
            t0 = d0; t1 = d1; t2 = d2; t3 = d3;
            c1 = 0; c2 = 0; c3 = 0;
            x  = valor;

            // Unidades
            t0 = t0 + (x % 10);
            if (t0 >= 10) begin t0 = t0 - 10; c1 = 1; end

            // Dezenas
            t1 = t1 + (x / 10) + c1;
            if (t1 >= 10) begin t1 = t1 - 10; c2 = 1; end

            // Centenas
            t2 = t2 + c2;
            if (t2 >= 10) begin t2 = t2 - 10; c3 = 1; end

            // Milhares
            t3 = t3 + c3;

            d0 <= t0; d1 <= t1; d2 <= t2; d3 <= t3;
        end
    end

    function [6:0] seg7;
        input [3:0] n;
        begin
            case(n)
                4'd0: seg7 = 7'b1000000;
                4'd1: seg7 = 7'b1111001;
                4'd2: seg7 = 7'b0100100;
                4'd3: seg7 = 7'b0110000;
                4'd4: seg7 = 7'b0011001;
                4'd5: seg7 = 7'b0010010;
                4'd6: seg7 = 7'b0000010;
                4'd7: seg7 = 7'b1111000;
                4'd8: seg7 = 7'b0000000;
                4'd9: seg7 = 7'b0010000;
                default: seg7 = 7'b1111111;
            endcase
        end
    endfunction

    assign HEX0 = seg7(d0);
    assign HEX1 = seg7(d1);
    assign HEX2 = seg7(d2);
    assign HEX3 = seg7(d3);

    assign HEX4 = seg7(v0); // Valor do veículo - unidades
    assign HEX5 = seg7(v1); // Valor do veículo - dezenas

    assign HEX7 = 7'b1111111; // desligado

endmodule

tb_pedagio.v
`timescale 1ns/1ns
`include "DE2_115.v"
module tb_pedagio;

    // Entradas
    reg [3:0] KEY;
    reg [17:0] SW;

    // Saídas
    wire [6:0] HEX0, HEX1, HEX2, HEX3, HEX4, HEX5, HEX6, HEX7;

    DE2_115 DUT (
        .KEY(KEY),
        .SW(SW),
        .HEX0(HEX0),
        .HEX1(HEX1),
        .HEX2(HEX2),
        .HEX3(HEX3),
        .HEX4(HEX4),
        .HEX5(HEX5),
        .HEX6(HEX6),
        .HEX7(HEX7)
    );

    // Clock 
    initial begin
        KEY = 4'b0000;
        SW = 18'b0;
        #5;
    end

    // Função para simular pressionamento de KEY[0]
    task pulse_key0;
    begin
        KEY[0] = 1; #10;
        KEY[0] = 0; #5;
    end
    endtask

    // Função para resetar (KEY[2])
    task reset_total;
    begin
        KEY[2] = 0; #10;
        KEY[2] = 1; #5;
    end
    endtask

    initial begin
        $dumpfile("pedagio_sim.vcd");
        $dumpvars(0, tb_pedagio);

        $monitor("T=%0t | KEY=%b | SW(E,P)=%b,%d | HEX6(Cat)=%b | HEX5,HEX4(Valor)=%b,%b | HEX3..0(Total)=%b,%b,%b,%b",
                 $time, KEY, SW[1:0], SW[5:2], HEX6, HEX5, HEX4, HEX3, HEX2, HEX1, HEX0);
    end

    initial begin
        // Reset inicial
        reset_total();

        // TESTE 1: Categoria 1, Valor 10
        $display("\n--- [T1] C1 (10) ---");
        SW[1:0] = 2'b00; // Eixos
        SW[5:2] = 4'd5;  // Peso
        #5;
        pulse_key0();
        #10;

        // TESTE 2: Categoria 3, Valor 50
        $display("\n--- [T2] C3 (50) ---");
        SW[1:0] = 2'b10; // Eixos
        SW[5:2] = 4'd13; // Peso
        #5;
        pulse_key0();
        #10;

        // TESTE 3: Categoria 2, Valor 25
        $display("\n--- [T3] C2 (25) ---");
        SW[1:0] = 2'b01; 
        SW[5:2] = 4'd10;
        #5;
        pulse_key0();
        #10;

        // TESTE 4: Erro (Valor 0)
        $display("\n--- [T4] ERRO (0) ---");
        SW[1:0] = 2'b00;
        SW[5:2] = 4'd8;
        #5;
        pulse_key0();
        #10;

        // TESTE 5: Categoria 3
        $display("\n--- [T5] C3 (50) ---");
        SW[1:0] = 2'b11;
        SW[5:2] = 4'd15;
        #5;
        pulse_key0();
        #10;

        // TESTE 6: Categoria 2
        $display("\n--- [T6] C2 (25) ---");
        SW[1:0] = 2'b01;
        SW[5:2] = 4'd12;
        #5;
        pulse_key0();
        #10;

        // Finaliza simulação
        #50;
        $finish;
    end

endmodule

pedagio_sim.vcd
$date
	Wed Nov 26 19:03:01 2025
$end
$version
	Icarus Verilog
$end
$timescale
	1ns
$end
$scope module tb_pedagio $end
$var wire 7 ! HEX7 [6:0] $end
$var wire 7 " HEX6 [6:0] $end
$var wire 7 # HEX5 [6:0] $end
$var wire 7 $ HEX4 [6:0] $end
$var wire 7 % HEX3 [6:0] $end
$var wire 7 & HEX2 [6:0] $end
$var wire 7 ' HEX1 [6:0] $end
$var wire 7 ( HEX0 [6:0] $end
$var reg 4 ) KEY [3:0] $end
$var reg 18 * SW [17:0] $end
$scope module DUT $end
$var wire 36 + GPIO [35:0] $end
$var wire 7 , HEX6 [6:0] $end
$var wire 7 - HEX7 [6:0] $end
$var wire 4 . KEY [3:0] $end
$var wire 9 / LEDG [8:0] $end
$var wire 18 0 LEDR [17:0] $end
$var wire 18 1 SW [17:0] $end
$var wire 4 2 peso [3:0] $end
$var wire 2 3 eixos [1:0] $end
$var wire 7 4 HEX5 [6:0] $end
$var wire 7 5 HEX4 [6:0] $end
$var wire 7 6 HEX3 [6:0] $end
$var wire 7 7 HEX2 [6:0] $end
$var wire 7 8 HEX1 [6:0] $end
$var wire 7 9 HEX0 [6:0] $end
$var reg 1 : c1 $end
$var reg 1 ; c2 $end
$var reg 1 < c3 $end
$var reg 7 = cat [6:0] $end
$var reg 4 > d0 [3:0] $end
$var reg 4 ? d1 [3:0] $end
$var reg 4 @ d2 [3:0] $end
$var reg 4 A d3 [3:0] $end
$var reg 4 B t0 [3:0] $end
$var reg 4 C t1 [3:0] $end
$var reg 4 D t2 [3:0] $end
$var reg 4 E t3 [3:0] $end
$var reg 4 F v0 [3:0] $end
$var reg 4 G v1 [3:0] $end
$var reg 8 H valor [7:0] $end
$var integer 32 I x [31:0] $end
$scope function seg7 $end
$var reg 4 J n [3:0] $end
$upscope $end
$upscope $end
$scope task pulse_key0 $end
$upscope $end
$scope task reset_total $end
$upscope $end
$upscope $end
$enddefinitions $end
$comment Show the parameter values. $end
$dumpall
$end
#0
$dumpvars
b1 J
bx I
b1010 H
b1 G
b0 F
bx E
bx D
bx C
bx B
b0 A
b0 @
b0 ?
b0 >
b1111001 =
x<
x;
x:
b1000000 9
b1000000 8
b1000000 7
b1000000 6
b1000000 5
b1111001 4
b0 3
b0 2
b0 1
bz 0
bz /
b0 .
b1111111 -
b1111001 ,
bz +
b0 *
b0 )
b1000000 (
b1000000 '
b1000000 &
b1000000 %
b1000000 $
b1111001 #
b1111001 "
b1111111 !
$end
#10
b100 )
b100 .
#15
b101 2
b10100 *
b10100 1
#20
b1111001 '
b1111001 8
b1 ?
b1010 I
0<
0;
0:
b0 E
b0 D
b1 C
b0 B
b101 )
b101 .
#30
b100 )
b100 .
#45
b10010 #
b10010 4
b101 J
b101 G
b110010 H
b110000 "
b110000 ,
b110000 =
b1101 2
b10 3
b110110 *
b110110 1
#50
b10 '
b10 8
b110 J
b110 ?
b110 C
b110010 I
b101 )
b101 .
#60
b100 )
b100 .
#75
b100100 #
b100100 4
b10010 $
b10010 5
b10 J
b10 G
b101 F
b11001 H
b100100 "
b100100 ,
b100100 =
b1010 2
b1 3
b101001 *
b101001 1
#80
b0 '
b0 8
b10010 (
b10010 9
b1000 J
b1000 ?
b101 >
b1000 C
b101 B
b11001 I
b101 )
b101 .
#90
b100 )
b100 .
#105
b1000000 #
b1000000 4
b1000000 $
b1000000 5
b0 J
b0 G
b0 F
b0 H
b110 "
b110 ,
b110 =
b1000 2
b0 3
b100000 *
b100000 1
#110
b0 I
b101 )
b101 .
#120
b100 )
b100 .
#135
b10010 #
b10010 4
b101 J
b101 G
b110010 H
b110000 "
b110000 ,
b110000 =
b1111 2
b11 3
b111111 *
b111111 1
#140
b1111001 &
b1111001 7
b110000 '
b110000 8
b1 J
b1 @
b11 ?
b1 D
1;
b11 C
b110010 I
b101 )
b101 .
#150
b100 )
b100 .
#165
b100100 #
b100100 4
b10010 $
b10010 5
b10 J
b10 G
b101 F
b11001 H
b100100 "
b100100 ,
b100100 =
b1100 2
b1 3
b110001 *
b110001 1
#170
b10 '
b10 8
b1000000 (
b1000000 9
b110 J
b110 ?
b0 >
b110 C
1:
b0 B
b11001 I
0;
b101 )
b101 .
#180
b100 )
b100 .
